sf_apm_lib/__init__.py
sf_apm_lib/snappyflow.py
sf_apm_lib-0.1.6.dist-info/LICENSE
sf_apm_lib-0.1.6.dist-info/METADATA
sf_apm_lib-0.1.6.dist-info/WHEEL
sf_apm_lib-0.1.6.dist-info/top_level.txt
sf_apm_lib-0.1.6.dist-info/RECORD
