Metadata-Version: 2.1
Name: sf_apm_lib
Version: 0.1.6
Summary: Snappyflow pip package
Home-page: https://github.com/snappyflow/py_snappyflow
Author: Maplelabs
Author-email: pradeep.jaiswar@maplelabs.com
License: MIT
Classifier: Development Status :: 2 - Pre-Alpha
Classifier: License :: OSI Approved :: MIT License
Classifier: Programming Language :: Python
Classifier: Programming Language :: Python :: 3
Classifier: Programming Language :: Python :: 3.4
Classifier: Programming Language :: Python :: 3.5
Classifier: Programming Language :: Python :: 3.6
Classifier: Programming Language :: Python :: 3.7
License-File: LICENSE
Requires-Dist: cryptography
Requires-Dist: pycryptodome ==3.10.1
Requires-Dist: cffi ==1.14.6
Requires-Dist: PyYAML ==5.4.1
